Nina_test/__init__.py
Nina_test/nico_version_selector.py
Nina_test/np.py
Nina_test/pd.py
Nina_test-2021.0.dist-info/METADATA
Nina_test-2021.0.dist-info/WHEEL
Nina_test-2021.0.dist-info/top_level.txt
Nina_test-2021.0.dist-info/RECORD
