Metadata-Version: 2.1
Name: Nina-test
Version: 2021.0
Summary: A Python test module.
Home-page: UNKNOWN
Author: Hrishikesh Arun
Author-email: hrishikesh28arun@gmail.com
License: UNKNOWN
Keywords: learning
Platform: UNKNOWN
Classifier: Development Status :: 5 - Production/Stable
Classifier: Intended Audience :: Education
Classifier: Programming Language :: Python :: 3
Requires: pandas
Requires: numpy
